pyNNsMD/NNsMD.py
pyNNsMD/__init__.py
pyNNsMD/data/__init__.py
pyNNsMD/datasets/__init__.py
pyNNsMD/hypers/__init__.py
pyNNsMD/hypers/hyper_mlp_e.py
pyNNsMD/hypers/hyper_mlp_eg.py
pyNNsMD/hypers/hyper_mlp_g2.py
pyNNsMD/hypers/hyper_mlp_nac.py
pyNNsMD/hypers/hyper_mlp_nac2.py
pyNNsMD/hypers/hyper_schnet_e.py
pyNNsMD/layers/__init__.py
pyNNsMD/layers/features.py
pyNNsMD/layers/gradients.py
pyNNsMD/layers/mlp.py
pyNNsMD/layers/normalize.py
pyNNsMD/models/__init__.py
pyNNsMD/models/mlp_e.py
pyNNsMD/models/mlp_eg.py
pyNNsMD/models/mlp_g2.py
pyNNsMD/models/mlp_nac.py
pyNNsMD/models/mlp_nac2.py
pyNNsMD/models/schnet_e.py
pyNNsMD/plots/__init__.py
pyNNsMD/plots/error.py
pyNNsMD/plots/loss.py
pyNNsMD/plots/pred.py
pyNNsMD/scaler/__init__.py
pyNNsMD/scaler/base.py
pyNNsMD/scaler/energy.py
pyNNsMD/scaler/nac.py
pyNNsMD/src/__init__.py
pyNNsMD/src/device.py
pyNNsMD/src/fit.py
pyNNsMD/src/selection.py
pyNNsMD/training/__init__.py
pyNNsMD/training/training_mlp_e.py
pyNNsMD/training/training_mlp_eg.py
pyNNsMD/training/training_mlp_g2.py
pyNNsMD/training/training_mlp_nac.py
pyNNsMD/training/training_mlp_nac2.py
pyNNsMD/training/training_schnet_e.py
pyNNsMD/utils/__init__.py
pyNNsMD/utils/activ.py
pyNNsMD/utils/callbacks.py
pyNNsMD/utils/data.py
pyNNsMD/utils/loss.py
pyNNsMD-2.0.0.dist-info/LICENSE
pyNNsMD-2.0.0.dist-info/METADATA
pyNNsMD-2.0.0.dist-info/WHEEL
pyNNsMD-2.0.0.dist-info/top_level.txt
pyNNsMD-2.0.0.dist-info/RECORD
