Metadata-Version: 2.1
Name: pyNNsMD
Version: 2.0.0
Summary: Neural Network for learning potential energy surface for molecular dynamics.
Home-page: UNKNOWN
Author: Patrick Reiser
Author-email: patrick.reiser@kit.edu
License: UNKNOWN
Keywords: materials,science,machine,learning,deep,dynamics,molecular,potential
Platform: UNKNOWN
Classifier: Programming Language :: Python :: 3
Classifier: Operating System :: OS Independent
Classifier: Intended Audience :: Science/Research
Classifier: Topic :: Scientific/Engineering :: Information Analysis
Classifier: Topic :: Scientific/Engineering :: Physics
Classifier: Topic :: Scientific/Engineering :: Chemistry
Classifier: Topic :: Software Development :: Libraries :: Python Modules
License-File: LICENSE
Requires-Dist: numpy
Requires-Dist: scikit-learn
Requires-Dist: matplotlib
Requires-Dist: kgcnn
Provides-Extra: tf
Requires-Dist: tensorflow (>=2.3.0) ; extra == 'tf'
Provides-Extra: tf_gpu
Requires-Dist: tensorflow-gpu (>=2.3.0) ; extra == 'tf_gpu'
